{"pin":"128555213","timestamp":1781783829604,"version":"4.0.0","data":{"gold":100,"goldPerKill":3,"stage":1,"wave":1,"soundMuted":false,"bgmEnabled":true,"bgmVolume":0.5,"sfxEnabled":true,"sfxVolume":0.7,"heroes":[{"id":"hero_knight","classId":"knight","level":1,"exp":0,"expToNext":100,"skills":["shield_bash","holy_shield","war_cry","iron_wall"],"equip":{},"skillLevels":{"shield_bash":1},"skillPoints":2},{"id":"hero_mage","classId":"mage","level":1,"exp":0,"expToNext":100,"skills":["fireball","frost_nova","arcane_blast","mana_shield"],"equip":{},"skillLevels":{"fireball":1},"skillPoints":2}],"team":{"front":{"id":"hero_knight","classId":"knight","level":1,"exp":0,"expToNext":100,"skills":["shield_bash","holy_shield","war_cry","iron_wall"],"equip":{},"skillLevels":{"shield_bash":1},"skillPoints":2},"back1":{"id":"hero_mage","classId":"mage","level":1,"exp":0,"expToNext":100,"skills":["fireball","frost_nova","arcane_blast","mana_shield"],"equip":{},"skillLevels":{"fireball":1},"skillPoints":2},"back2":null,"back3":null},"unlockedSlots":2,"inventory":[],"maxInventory":100,"warehouseExpandLevels":0,"maxStage":1,"talents":[],"gems":[],"forgeDust":0,"reforgestone":0,"totalPlayTime":0,"monstersKilled":0,"achievements":{},"totalKills":0,"totalGoldEarned":0,"totalEquipObtained":0,"totalFuse":0,"maxTowerFloor":0,"highestEnhanceLevel":0,"lastSaveTime":1781783823514,"autoProcess":{"enabled":false,"qualities":[],"action":"sell"},"stamina":64,"lastStaminaTime":1781783793514,"lotteryStone":0,"upgradeStone":0,"tower":{"currentFloor":1,"maxFloor":1,"bestFloor":1,"totalRuns":0,"totalDeaths":0,"lastReward":null},"lotteryHistory":[],"equipCodex":{},"rebirthPoints":0,"rebirthBonuses":{},"rebirthCount":0,"hasRebirthed":false,"slotLevels":{},"campResources":{"herbs":0,"ore":0,"lastCollectTime":0},"monsterBonds":{},"activeCampBuff":null,"materials":{"herb":0,"ore":0,"forgeDust":0,"reforgestone":0,"lotteryStone":0,"upgradeStone":0,"gem":0},"dailyKills":0,"dailyStages":0,"dailyDungeons":0,"dailyDecompose":0,"dailyGoldEarned":0,"_dailyQuestDate":"Thu Jun 18 2026","_dailyQuestClaimed":{},"pets":[],"activePets":[],"petFood":0,"petShards":{},"petStars":{},"petEggStones":0,"petIncubators":[{"tier":null,"hatchTime":0},{"tier":null,"hatchTime":0},{"tier":null,"hatchTime":0}],"petEggStorage":[],"version":"4.0.0","_migratedFrom":"0.0.0","petSlotsFromTalent":0}}